[
    {
        "modify":1401417616575,
        "url":"http://news.dolphin.com/detail.html?feature=105&from=top#detail1405328016781434",
        "title":"周润发王诗龄头戴红花合影卖萌 发哥见萌娃一秒变呆萌！"
    },
    {
        "modify":1401417616575,
        "url":"http://news.dolphin.com/detail.html?feature=1&from=top#detail1403483565059382",
        "title":"女协警自称遭强暴 涉事警官被关禁闭"
    },
    {
        "modify":1401417616575,
        "url":"http://news.dolphin.com/detail.html?feature=1&from=top#detail1403478451640431",
        "title":"揭秘虐童国学老师的双面人生"
    }
]